clockwise/__init__.py
clockwise/interface.py
clockwise/io.py
clockwise-1.0.4.dist-info/LICENSE
clockwise-1.0.4.dist-info/METADATA
clockwise-1.0.4.dist-info/WHEEL
clockwise-1.0.4.dist-info/top_level.txt
clockwise-1.0.4.dist-info/RECORD
