Metadata-Version: 2.1
Name: clockwise
Version: 1.0.4
Summary: A simple timing library for Python
Author-email: Simon Schaefer <simon.k.schaefer@gmail.com>
Maintainer-email: Simon Schaefer <simon.k.schaefer@gmail.com>
Keywords: profiling
Classifier: Development Status :: 5 - Production/Stable
Classifier: Intended Audience :: Developers
Classifier: License :: OSI Approved :: MIT License
Requires-Python: >=3.0
License-File: LICENSE
